MANIFEST.in
README.md
setup.cfg
setup.py
version
src/ds_billing_app.egg-info/PKG-INFO
src/ds_billing_app.egg-info/SOURCES.txt
src/ds_billing_app.egg-info/dependency_links.txt
src/ds_billing_app.egg-info/entry_points.txt
src/ds_billing_app.egg-info/requires.txt
src/ds_billing_app.egg-info/top_level.txt
src/promo_consolidation/__init__.py
src/promo_consolidation/ibms.py
src/promo_consolidation/ibms_feeds.py
src/promo_consolidation/ibms_feeds_new.py
src/promo_consolidation/ireg_parser_test3.py
src/y2k/DSO.py
src/y2k/__init__.py
src/y2k/bq_client.py
src/y2k/cash_sheets.py
src/y2k/discrepancies.py
src/y2k/query_statements.py